makeover/__init__.py
makeover/__main__.py
makeover/app.py
makeover/config.py
makeover/utils.py
makeover/viz_gen.py
makeover-0.0.2.dist-info/METADATA
makeover-0.0.2.dist-info/WHEEL
makeover-0.0.2.dist-info/entry_points.txt
makeover-0.0.2.dist-info/top_level.txt
makeover-0.0.2.dist-info/RECORD
