Metadata-Version: 2.1
Name: makeover
Version: 0.0.2
Summary: this package automatically generates visualization dashboard of given data
Home-page: https://github.com/zahash/makeover
Author: zahash
Author-email: zahash.z@gmail.com
License: MIT
Platform: UNKNOWN
Classifier: License :: OSI Approved :: MIT License
Classifier: Programming Language :: Python :: 3
Classifier: Programming Language :: Python :: 3.7
Requires-Dist: pandas
Requires-Dist: dash
Requires-Dist: statsmodels
